spark/__init__.py
spark/agents/__init__.py
spark/agents/agent.py
spark/agents/config.py
spark/agents/cost_tracker.py
spark/agents/memory.py
spark/agents/strategies.py
spark/agents/strategy_registry.py
spark/agents/types.py
spark/graphs/__init__.py
spark/graphs/base.py
spark/graphs/event_bus.py
spark/graphs/graph.py
spark/graphs/graph_state.py
spark/graphs/tasks.py
spark/kit/README.md
spark/kit/__init__.py
spark/kit/analysis.py
spark/kit/codegen.py
spark/kit/diff.py
spark/kit/loader.py
spark/kit/spec_cli.py
spark/kit/validation.py
spark/models/__init__.py
spark/models/base.py
spark/models/bedrock.py
spark/models/cache.py
spark/models/echo.py
spark/models/exceptions.py
spark/models/gemini.py
spark/models/openai.py
spark/models/types.py
spark/models/utils.py
spark/nodes/__init__.py
spark/nodes/base.py
spark/nodes/capabilities.py
spark/nodes/channels.py
spark/nodes/config.py
spark/nodes/exceptions.py
spark/nodes/human.py
spark/nodes/nodes.py
spark/nodes/policies.py
spark/nodes/rpc.py
spark/nodes/serde.py
spark/nodes/spec.py
spark/nodes/types.py
spark/tools/__init__.py
spark/tools/decorator.py
spark/tools/executor.py
spark/tools/registry.py
spark/tools/tools.py
spark/tools/types.py
spark/utils/__init__.py
spark/utils/common.py
spark/utils/import_utils.py
spark-0.3.1.dist-info/METADATA
spark-0.3.1.dist-info/WHEEL
spark-0.3.1.dist-info/RECORD
